seddy/__init__.py
seddy/__main__.py
seddy/_util.py
seddy/decider.py
seddy/registration.py
seddy/_specs/__init__.py
seddy/_specs/_base.py
seddy/_specs/_dag.py
seddy/_specs/_io.py
seddy-0.3.0a1.dist-info/licenses/LICENSE
seddy-0.3.0a1.dist-info/METADATA
seddy-0.3.0a1.dist-info/WHEEL
seddy-0.3.0a1.dist-info/entry_points.txt
seddy-0.3.0a1.dist-info/top_level.txt
seddy-0.3.0a1.dist-info/RECORD
