Metadata-Version: 2.4
Name: seddy
Version: 0.3.0a1
Summary: Multi-workflow SWF Decider and Workflow Management Service
Home-page: https://github.com/EpicWink/seddy
Author: Laurie O
Author-email: laurie_opperman@hotmail.com
Project-URL: Documentation, https://seddy.readthedocs.io/en/latest/
Project-URL: Source, https://github.com/EpicWink/seddy
Project-URL: Tracker, https://github.com/EpicWink/seddy/issues
Keywords: swf,decider
Classifier: Development Status :: 4 - Beta
Classifier: Environment :: Console
Classifier: Intended Audience :: Developers
Classifier: License :: OSI Approved :: MIT License
Classifier: Programming Language :: Python :: 3 :: Only
Classifier: Natural Language :: English
Classifier: Operating System :: POSIX :: Linux
Classifier: Operating System :: Microsoft :: Windows
Classifier: Topic :: Software Development
Classifier: Topic :: System :: Distributed Computing
Classifier: Typing :: Typed
Requires-Python: ~=3.6
License-File: LICENSE
Requires-Dist: boto3
Requires-Dist: dataclasses; python_version < "3.7"
Requires-Dist: importlib-metadata; python_version < "3.8"
Dynamic: license-file
